<?xml version="1.0" encoding="UTF-8" ?><info><doc_link type="str">https://www.fips.ru/publication-web/publications/document?type=doc&amp;tab=UsrTM&amp;id=1D2703E7-28AA-4E10-8826-E7AE0F21172F</doc_link><doc_num type="str">ru 880009</doc_num><doc_name type="str">Сведения о государственной регистрации товарного знака</doc_name><small_image_link type="str">https://www1.fips.ru/ofpstorage/Doc/TM/RUNWTM/000/000/088/000/900/%D0%A2%D0%97-880009-00001/00000001_m.jpg</small_image_link><doc_desc type="str">Номер заявки: 2022707121Дата подачи заявки: 07.02.2022</doc_desc><doc_public_date type="str">07.07.2022</doc_public_date><doc_reg_date type="str">07.07.2022</doc_reg_date><pdf_link type="str">https://www1.fips.ru/ofpstorage/Doc/TM/RUNWTM/000/000/088/000/900/%D0%A2%D0%97-880009-00001/DOCUMENT.PDF</pdf_link><big_image_link type="str">https://www1.fips.ru/ofpstorage/Doc/TM/RUNWTM/000/000/088/000/900/%D0%A2%D0%97-880009-00001//00000001.jpg</big_image_link><key name="591_colors" type="str"></key><key name="526_noprotected" type="str"></key><key name="511_MKTU" type="str">30, 35</key></info>